my_first_plugin/__init__.py
my_first_plugin/my_first_plugin.py
my_first_plugin_goahead_jakemyday-0.0.1.dist-info/LICENSE
my_first_plugin_goahead_jakemyday-0.0.1.dist-info/METADATA
my_first_plugin_goahead_jakemyday-0.0.1.dist-info/WHEEL
my_first_plugin_goahead_jakemyday-0.0.1.dist-info/top_level.txt
my_first_plugin_goahead_jakemyday-0.0.1.dist-info/RECORD
