Metadata-Version: 2.1
Name: my_first_plugin-goahead_jakemyday
Version: 0.0.1
Summary: A small example package to learn how to upload packages
Home-page: https://github.com/jakemackinlay/opensesame_plugin_0.1
Author: Jake Mackinlay
Author-email: jmackinlay@lumination.com.au
License: UNKNOWN
Platform: UNKNOWN
Classifier: Programming Language :: Python :: 3
Classifier: License :: OSI Approved :: MIT License
Classifier: Operating System :: OS Independent
Requires-Python: >=3.6
License-File: LICENSE
